pytest_funcnodes/__init__.py
pytest_funcnodes/nodetest_decorator.py
pytest_funcnodes/plugin.py
pytest_funcnodes/subtests.py
pytest_funcnodes/testingsystem.py
pytest_funcnodes-1.1.0.dist-info/licenses/LICENSE
pytest_funcnodes-1.1.0.dist-info/METADATA
pytest_funcnodes-1.1.0.dist-info/WHEEL
pytest_funcnodes-1.1.0.dist-info/entry_points.txt
pytest_funcnodes-1.1.0.dist-info/top_level.txt
pytest_funcnodes-1.1.0.dist-info/RECORD
