Metadata-Version: 2.4
Name: pytest-funcnodes
Version: 1.1.0
Summary: Testing plugin for funcnodes
Author-email: Julian Kimmig <julian.kimmig@linkdlab.de>
Maintainer-email: Julian Kimmig <julian.kimmig@linkdlab.de>
License:                     GNU AFFERO GENERAL PUBLIC LICENSE
Project-URL: Repository, https://github.com/Linkdlab/funcnodes_pytest
Classifier: Framework :: Pytest
Classifier: Development Status :: 4 - Beta
Classifier: Intended Audience :: Developers
Classifier: Topic :: Software Development :: Testing
Classifier: Operating System :: OS Independent
Classifier: License :: OSI Approved :: GNU Affero General Public License v3 or later (AGPLv3+)
Requires-Python: >=3.11
License-File: LICENSE
Requires-Dist: funcnodes-core>=2.0.0a3
Requires-Dist: pytest>=6.2.0
Requires-Dist: pytest-asyncio>=0.24.0
Dynamic: license-file
